analyze_drafter_site/__init__.py
analyze_drafter_site/__main__.py
analyze_drafter_site/base.py
analyze_drafter_site/cli.py
analyze_drafter_site/details.py
analyze_drafter_site/visitor.py
analyze_drafter_site/complexity/__init__.py
analyze_drafter_site/complexity/complexity.py
analyze_drafter_site/complexity/diagnostics.py
analyze_drafter_site/complexity/extents.py
analyze_drafter_site/complexity/score_loader.py
analyze_drafter_site/complexity/strings.py
analyze_drafter_site-0.4.1.dist-info/LICENSE
analyze_drafter_site-0.4.1.dist-info/METADATA
analyze_drafter_site-0.4.1.dist-info/WHEEL
analyze_drafter_site-0.4.1.dist-info/entry_points.txt
analyze_drafter_site-0.4.1.dist-info/top_level.txt
analyze_drafter_site-0.4.1.dist-info/RECORD
