Metadata-Version: 2.1
Name: analyze-drafter-site
Version: 0.4.1
Summary: A python tool for analyzing and summarizing a Drafter website in various ways, to simplify grading
Home-page: https://github.com/drafter-edu/analyze-drafter-site/
Author: drafter-edu
License-File: LICENSE
Requires-Dist: click
Requires-Dist: drafter
Provides-Extra: test
Requires-Dist: pytest; extra == "test"
Requires-Dist: coverage; extra == "test"
Requires-Dist: flake8; extra == "test"
Requires-Dist: black; extra == "test"
Requires-Dist: isort; extra == "test"
Requires-Dist: pytest-cov; extra == "test"
Requires-Dist: mypy; extra == "test"
Requires-Dist: gitchangelog; extra == "test"
Requires-Dist: mkdocs; extra == "test"
Requires-Dist: pytest-datadir; extra == "test"
